decoy/__init__.py
decoy/call_handler.py
decoy/context_managers.py
decoy/core.py
decoy/errors.py
decoy/matchers.py
decoy/mypy/__init__.py
decoy/mypy/plugin.py
decoy/py.typed
decoy/pytest_plugin.py
decoy/spy.py
decoy/spy_core.py
decoy/spy_events.py
decoy/spy_log.py
decoy/stringify.py
decoy/stub_store.py
decoy/types.py
decoy/verifier.py
decoy/warning_checker.py
decoy/warnings.py
decoy-2.3.0.dist-info/WHEEL
decoy-2.3.0.dist-info/entry_points.txt
decoy-2.3.0.dist-info/METADATA
decoy-2.3.0.dist-info/RECORD
