Metadata-Version: 2.4
Name: decoy
Version: 2.3.0
Summary: Opinionated mocking library for Python
Author: Michael Cousins
Author-email: Michael Cousins <michael@cousins.io>>
License-Expression: MIT
Classifier: Development Status :: 5 - Production/Stable
Classifier: Intended Audience :: Developers
Classifier: Operating System :: OS Independent
Classifier: Topic :: Software Development :: Testing
Classifier: Topic :: Software Development :: Testing :: Mocking
Classifier: Typing :: Typed
Requires-Python: >=3.7
Project-URL: Changelog, https://github.com/mcous/decoy/releases
Project-URL: Documentation, https://michael.cousins.io/decoy/
Project-URL: Homepage, https://michael.cousins.io/decoy/
Project-URL: Issues, https://github.com/mcous/decoy/issues
Project-URL: Repository, https://github.com/mcous/decoy
